setup.cfg
setup.py
tinyblox/__init__.py
tinyblox/cassandrax.py
tinyblox/logx.py
tinyblox/openstackx.py
tinyblox/ovsx.py
tinyblox/remotex.py
tinyblox/toolx.py
tinyblox.egg-info/PKG-INFO
tinyblox.egg-info/SOURCES.txt
tinyblox.egg-info/dependency_links.txt
tinyblox.egg-info/requires.txt
tinyblox.egg-info/top_level.txt