Metadata-Version: 1.1
Name: tinyblox
Version: 0.1.14
Summary: collection of api blocks written in python to help speedup automation
Home-page: https://github.com/DreamForgeContrive/tinyblox
Author: Kiran Vemuri
Author-email: kkvemuri@uh.edu
License: MIT
Download-URL: https://github.com/DreamForgeContrive/tinyblox/tarball/0.1.14
Keywords: automation,ssh,sftp,openstack,logging,cassandra
Platform: UNKNOWN
